setup.py
logmatic/__init__.py
logmatic_python.egg-info/PKG-INFO
logmatic_python.egg-info/SOURCES.txt
logmatic_python.egg-info/dependency_links.txt
logmatic_python.egg-info/requires.txt
logmatic_python.egg-info/top_level.txt