Metadata-Version: 1.0
Name: logmatic-python
Version: 0.0.6
Summary: Python plugin to send logs to Logmatic.io
Home-page: https://github.com/logmatic/logmatic-python
Author: Logmatic.io support team
Author-email: support@logmatic.io
License: MIT
Platform: UNKNOWN
